rcatool/__init__.py
rcatool/config/SAMPLE_observations_metadata.py
rcatool/config/config_main.ini
rcatool/config/observations_metadata_Freja.py
rcatool/config/observations_metadata_atos.py
rcatool/plot/__init__.py
rcatool/plot/colors.py
rcatool/plot/plots.py
rcatool/runtime/RCAT_main.py
rcatool/runtime/RCAT_plots.py
rcatool/runtime/RCAT_stats.py
rcatool/runtime/__init__.py
rcatool/stats/ASoP.py
rcatool/stats/__init__.py
rcatool/stats/arithmetics.py
rcatool/stats/bootstrap.py
rcatool/stats/climateindex.py
rcatool/stats/convolve.py
rcatool/stats/event_duration.py
rcatool/stats/pdf.py
rcatool/stats/precipitation_index.py
rcatool/stats/sal.py
rcatool/stats/t_test.py
rcatool/utils/__init__.py
rcatool/utils/atmosphys.py
rcatool/utils/draw_polygon.py
rcatool/utils/file_io.py
rcatool/utils/grids.py
rcatool/utils/ini_reader.py
rcatool/utils/polygons.py
rcatool/utils/polygon_files/Alps.txt
rcatool/utils/polygon_files/BIODiv_support_model_domain.txt
rcatool/utils/polygon_files/Baltic_Sea.txt
rcatool/utils/polygon_files/Baltic_Sea_Coast.txt
rcatool/utils/polygon_files/Baltic_Sea_Large.txt
rcatool/utils/polygon_files/Baltic_Sea_analysis_domain.txt
rcatool/utils/polygon_files/Bay_of_Bothnia.txt
rcatool/utils/polygon_files/Bay_of_Bothnia_Coast.txt
rcatool/utils/polygon_files/Bay_of_Bothnia_analysis_domain.txt
rcatool/utils/polygon_files/Black_Sea.txt
rcatool/utils/polygon_files/British_Isles.txt
rcatool/utils/polygon_files/Central_Europe.txt
rcatool/utils/polygon_files/Copenhagen.txt
rcatool/utils/polygon_files/CopenhagenLarge.txt
rcatool/utils/polygon_files/Denmark.txt
rcatool/utils/polygon_files/East_Europe.txt
rcatool/utils/polygon_files/EuroAtlantic.txt
rcatool/utils/polygon_files/Fenno-Scandinavia.txt
rcatool/utils/polygon_files/Finland.txt
rcatool/utils/polygon_files/France.txt
rcatool/utils/polygon_files/Germany.txt
rcatool/utils/polygon_files/HelsinkiLarge.txt
rcatool/utils/polygon_files/Iberian_peninsula.txt
rcatool/utils/polygon_files/JamtlandsLan.txt
rcatool-0.1.3.dist-info/METADATA
rcatool-0.1.3.dist-info/WHEEL
rcatool-0.1.3.dist-info/licenses/AUTHORS.md
rcatool-0.1.3.dist-info/licenses/LICENSE
rcatool-0.1.3.dist-info/RECORD
