Metadata-Version: 2.3
Name: rcatool
Version: 0.1.3
Summary: The Regional Climate Analysis Tool (RCAT), is a tool to calculate and visualize weather and climate model statistics.
Project-URL: Homepage, https://regional-climate-analysis-tool.readthedocs.io/en/latest/
Project-URL: Source, https://github.com/jplind79/RCAT
Project-URL: Issues, https://github.com/jplind79/RCAT/issues
Author-email: Petter Lind <petter.lind@smhi.se>
Maintainer-email: Petter Lind <petter.lind@smhi.se>
License: MIT License
License-File: AUTHORS.md
License-File: LICENSE
Keywords: climate,dask,diagnostic,interpolation,model,numpy,plotting,python,science,statistics,xarray
Classifier: Development Status :: 3 - Alpha
Classifier: Intended Audience :: Science/Research
Classifier: License :: OSI Approved :: MIT License
Classifier: Operating System :: OS Independent
Classifier: Programming Language :: Python :: 3
Classifier: Topic :: Scientific/Engineering :: Atmospheric Science
Requires-Python: >=3.10
Requires-Dist: cartopy
Requires-Dist: dask-jobqueue
Requires-Dist: dask[complete]
Requires-Dist: esmpy
Requires-Dist: h5netcdf
Requires-Dist: matplotlib
Requires-Dist: netcdf4
Requires-Dist: numpy
Requires-Dist: xarray
Requires-Dist: xesmf
